thisapidoesnotexist/__init__.py
thisapidoesnotexist/image_classes.py
thisapidoesnotexist/image_download.py
thisapidoesnotexist-0.2.dist-info/LICENSE.md
thisapidoesnotexist-0.2.dist-info/METADATA
thisapidoesnotexist-0.2.dist-info/WHEEL
thisapidoesnotexist-0.2.dist-info/top_level.txt
thisapidoesnotexist-0.2.dist-info/RECORD
