Metadata-Version: 2.1
Name: thisapidoesnotexist
Version: 0.2
Summary: Api não oficial das páginas thispersondoesnotexist e thiscatdoesnotexist
Home-page: https://github.com/Arfafa/ThisApiDoesNotExist
Author: Miguel Lopes
Author-email: miguel.lopes.filho@protonmail.com
License: MIT License
